<annotation>
  <folder>jpg from jpeg</folder>
  <filename>39</filename>
  <path>C:\Users\Mustafa\Desktop\WINTER\EDP\Transfer LEarning\MARCH 8\jpg from jpeg\39.jpg</path>
  <source>
    <database>Unknown</database>
  </source>
  <size>
    <width>767</width>
    <height>767</height>
    <depth>3</depth>
  </size>
  <segmented>0</segmented>
  <object>
    <name>Speed Limit 60</name>
    <pose>Unspecified</pose>
    <truncated>0</truncated>
    <difficult>0</difficult>
    <bndbox>
      <xmin>296</xmin>
      <ymin>228</ymin>
      <xmax>447</xmax>
      <ymax>388</ymax>
    </bndbox>
  </object>
  <object>
    <name>Green Traffic Light</name>
    <pose>Unspecified</pose>
    <truncated>0</truncated>
    <difficult>0</difficult>
    <bndbox>
      <xmin>529</xmin>
      <ymin>80</ymin>
      <xmax>592</xmax>
      <ymax>238</ymax>
    </bndbox>
  </object>
  <object>
    <name>Stop Sign</name>
    <pose>Unspecified</pose>
    <truncated>0</truncated>
    <difficult>0</difficult>
    <bndbox>
      <xmin>604</xmin>
      <ymin>242</ymin>
      <xmax>753</xmax>
      <ymax>394</ymax>
    </bndbox>
  </object>
  <object>
    <name>Person</name>
    <pose>Unspecified</pose>
    <truncated>0</truncated>
    <difficult>0</difficult>
    <bndbox>
      <xmin>157</xmin>
      <ymin>399</ymin>
      <xmax>307</xmax>
      <ymax>594</ymax>
    </bndbox>
  </object>
  <object>
    <name>Red Traffic Light</name>
    <pose>Unspecified</pose>
    <truncated>0</truncated>
    <difficult>0</difficult>
    <bndbox>
      <xmin>148</xmin>
      <ymin>63</ymin>
      <xmax>207</xmax>
      <ymax>219</ymax>
    </bndbox>
  </object>
  <object>
    <name>Yellow Traffic Light</name>
    <pose>Unspecified</pose>
    <truncated>0</truncated>
    <difficult>0</difficult>
    <bndbox>
      <xmin>22</xmin>
      <ymin>63</ymin>
      <xmax>82</xmax>
      <ymax>212</ymax>
    </bndbox>
  </object>
</annotation>
