<annotation>
  <folder>test</folder>
  <filename>i65</filename>
  <path>C:\Users\Mustafa\Desktop\WINTER\EDP\Transfer LEarning\March 15 New Training Set\test\i65.jpeg</path>
  <source>
    <database>Unknown</database>
  </source>
  <size>
    <width>768</width>
    <height>768</height>
    <depth>3</depth>
  </size>
  <segmented>0</segmented>
  <object>
    <name>Person</name>
    <pose>Unspecified</pose>
    <truncated>0</truncated>
    <difficult>0</difficult>
    <bndbox>
      <xmin>118</xmin>
      <ymin>230</ymin>
      <xmax>349</xmax>
      <ymax>449</ymax>
    </bndbox>
  </object>
  <object>
    <name>Stop Sign</name>
    <pose>Unspecified</pose>
    <truncated>0</truncated>
    <difficult>0</difficult>
    <bndbox>
      <xmin>358</xmin>
      <ymin>253</ymin>
      <xmax>666</xmax>
      <ymax>499</ymax>
    </bndbox>
  </object>
</annotation>
